Metadata-Version: 2.1
Name: my_agent
Version: 0.1.0
Summary: Example LangGraph project for deployment to LangGraph Cloud
Author: langchain-ai
Requires-Python: >=3.9.0,<3.13
Classifier: Programming Language :: Python :: 3
Classifier: Programming Language :: Python :: 3.9
Classifier: Programming Language :: Python :: 3.10
Classifier: Programming Language :: Python :: 3.11
Classifier: Programming Language :: Python :: 3.12
Requires-Dist: langchain-cli (>=0.0.29,<0.0.30)
Requires-Dist: langchain_anthropic (>=0.1.0,<0.2.0)
Requires-Dist: langchain_community (>=0.2.0,<0.3.0)
Requires-Dist: langchain_core (>=0.2.0,<0.3.0)
Requires-Dist: langchain_openai (>=0.1.0,<0.2.0)
Requires-Dist: langgraph (>=0.2.0,<0.3.0)
Requires-Dist: langgraph-checkpoint-sqlite (>=1.0.0,<2.0.0)
Requires-Dist: langserve (>=0.2.2,<0.3.0)
Requires-Dist: neo4j-advanced-rag (>=0.1.0,<0.2.0)
Requires-Dist: neo4j-cypher (>=0.1.0,<0.2.0)
Requires-Dist: python-dotenv (>=1.0.1,<2.0.0)
Requires-Dist: tavily-python (>=0.3.0,<0.4.0)
